genetist/__init__.py
genetist/crossover.py
genetist/datatype_inference.py
genetist/environment.py
genetist/individual.py
genetist/mutation.py
genetist/parameters.py
genetist/results.py
genetist/utils.py
genetist-0.9.11.dist-info/LICENSE
genetist-0.9.11.dist-info/METADATA
genetist-0.9.11.dist-info/WHEEL
genetist-0.9.11.dist-info/top_level.txt
genetist-0.9.11.dist-info/RECORD
