Metadata-Version: 2.1
Name: genetist
Version: 0.9.11
Summary: Genetist: optimization with genetic algorithms
Home-page: https://github.com/unaiLopez/genetist
Author: Unai Lopez Ansoleaga
Author-email: unai19970315@gmail.com
License: MIT
Platform: UNKNOWN
Requires-Python: >=3.6
Requires-Dist: numpy (==1.21.3)
Requires-Dist: tqdm (==4.64.0)
Requires-Dist: pandas (==1.3.4)
